src/__init__.py
src/py.typed
src/server.py
src/data/__init__.py
src/data/index.py
src/data/loader.py
src/data/syncer.py
src/utils/__init__.py
src/utils/formatter.py
src/utils/validation.py
mcp_roblox_docs-3.3.0.dist-info/METADATA
mcp_roblox_docs-3.3.0.dist-info/WHEEL
mcp_roblox_docs-3.3.0.dist-info/entry_points.txt
mcp_roblox_docs-3.3.0.dist-info/RECORD
