Metadata-Version: 2.4
Name: mcp-roblox-docs
Version: 3.3.0
Summary: MCP Server for Roblox Studio Documentation - Complete API reference, FastFlags, Open Cloud API, Luau language docs, DataTypes, Libraries, DevForum search, and more
Author: Native
License: MIT
Keywords: api,datatypes,documentation,fastflags,luau,mcp,opencloud,roblox,studio
Requires-Python: >=3.11
Requires-Dist: httpx>=0.27.0
Requires-Dist: mcp[cli]>=1.2.0
Requires-Dist: orjson>=3.10.0
Requires-Dist: platformdirs>=4.0.0
Requires-Dist: pyyaml>=6.0
Provides-Extra: dev
Requires-Dist: pytest-asyncio>=0.23.0; extra == 'dev'
Requires-Dist: pytest>=8.0.0; extra == 'dev'
